[
    {
        "key": "group_62d52e56597e4",
        "title": "Banner",
        "fields": [
            {
                "key": "field_62d65d55c97a6",
                "label": "Billede",
                "name": "image",
                "type": "image",
                "instructions": "Vælg\/upload et billede",
                "required": 1,
                "conditional_logic": 0,
                "wrapper": {
                    "width": "",
                    "class": "",
                    "id": ""
                },
                "return_format": "array",
                "preview_size": "thumbnail",
                "library": "all",
                "min_width": "",
                "min_height": "",
                "min_size": "",
                "max_width": "",
                "max_height": "",
                "max_size": "",
                "mime_types": ""
            },
            {
                "key": "field_62d65d782fe1e",
                "label": "Tekst",
                "name": "text",
                "type": "wysiwyg",
                "instructions": "Indtast og formatter en kort banner tekst",
                "required": 1,
                "conditional_logic": 0,
                "wrapper": {
                    "width": "",
                    "class": "",
                    "id": ""
                },
                "default_value": "",
                "tabs": "all",
                "toolbar": "full",
                "media_upload": 0,
                "delay": 0
            }
        ],
        "location": [
            [
                {
                    "param": "block",
                    "operator": "==",
                    "value": "acf\/banner"
                }
            ]
        ],
        "menu_order": 0,
        "position": "normal",
        "style": "default",
        "label_placement": "top",
        "instruction_placement": "label",
        "hide_on_screen": "",
        "active": true,
        "description": "",
        "show_in_rest": 0
    },
    {
        "key": "group_62ea30301746f",
        "title": "Sider",
        "fields": [
            {
                "key": "field_62ea3033e31a5",
                "label": "Skal Kontakt formular vises i footer",
                "name": "show_contact_form",
                "type": "true_false",
                "instructions": "Vælg om kontakt formularen skal vises i footeren",
                "required": 0,
                "conditional_logic": 0,
                "wrapper": {
                    "width": "",
                    "class": "",
                    "id": ""
                },
                "message": "",
                "default_value": 0,
                "ui": 1,
                "ui_on_text": "Vis",
                "ui_off_text": "Skjul"
            },
            {
                "key": "field_62fcdf0984a5c",
                "label": "Kontakt formular tekst",
                "name": "contact_form_text",
                "type": "text",
                "instructions": "Skriv en kort sætning",
                "required": 0,
                "conditional_logic": 0,
                "wrapper": {
                    "width": "",
                    "class": "",
                    "id": ""
                },
                "default_value": "",
                "placeholder": "",
                "prepend": "",
                "append": "",
                "maxlength": ""
            }
        ],
        "location": [
            [
                {
                    "param": "post_type",
                    "operator": "==",
                    "value": "page"
                }
            ]
        ],
        "menu_order": 0,
        "position": "normal",
        "style": "default",
        "label_placement": "top",
        "instruction_placement": "label",
        "hide_on_screen": "",
        "active": true,
        "description": "",
        "show_in_rest": 0
    },
    {
        "key": "group_62f0eeb66c3e4",
        "title": "Slider [BLOCK]",
        "fields": [
            {
                "key": "field_62f0ef06c6249",
                "label": "Overskrift",
                "name": "heading",
                "type": "wysiwyg",
                "instructions": "Indtast en kort overskrift\/tekst",
                "required": 0,
                "conditional_logic": 0,
                "wrapper": {
                    "width": "",
                    "class": "",
                    "id": ""
                },
                "default_value": "",
                "tabs": "all",
                "toolbar": "full",
                "media_upload": 1,
                "delay": 0
            },
            {
                "key": "field_62f2362e12ead",
                "label": "Billede",
                "name": "image",
                "type": "image",
                "instructions": "Vælg\/Upload et billede",
                "required": 0,
                "conditional_logic": 0,
                "wrapper": {
                    "width": "",
                    "class": "",
                    "id": ""
                },
                "return_format": "array",
                "preview_size": "medium",
                "library": "all",
                "min_width": "",
                "min_height": "",
                "min_size": "",
                "max_width": "",
                "max_height": "",
                "max_size": "",
                "mime_types": ""
            },
            {
                "key": "field_630898b879bc7",
                "label": "Indholdstype",
                "name": "content",
                "type": "button_group",
                "instructions": "Vælg hvad der skal vises i slider",
                "required": 1,
                "conditional_logic": 0,
                "wrapper": {
                    "width": "",
                    "class": "",
                    "id": ""
                },
                "choices": {
                    "logo": "Virksomheds logoer",
                    "content": "Tekst indhold"
                },
                "allow_null": 0,
                "default_value": "logo",
                "layout": "horizontal",
                "return_format": "value"
            },
            {
                "key": "field_62f0ef17c624a",
                "label": "Vælg layout",
                "name": "layout",
                "type": "button_group",
                "instructions": "Vælg layout",
                "required": 0,
                "conditional_logic": [
                    [
                        {
                            "field": "field_630898b879bc7",
                            "operator": "==",
                            "value": "logo"
                        }
                    ]
                ],
                "wrapper": {
                    "width": "",
                    "class": "",
                    "id": ""
                },
                "choices": {
                    "all": "Alle",
                    "single": "Vælg enkle"
                },
                "allow_null": 0,
                "default_value": "",
                "layout": "horizontal",
                "return_format": "value"
            },
            {
                "key": "field_62f0ef38c624b",
                "label": "Vælg enkle",
                "name": "singles",
                "type": "post_object",
                "instructions": "",
                "required": 0,
                "conditional_logic": [
                    [
                        {
                            "field": "field_62f0ef17c624a",
                            "operator": "==",
                            "value": "single"
                        }
                    ]
                ],
                "wrapper": {
                    "width": "",
                    "class": "",
                    "id": ""
                },
                "post_type": [
                    "company"
                ],
                "taxonomy": "",
                "allow_null": 0,
                "multiple": 1,
                "return_format": "id",
                "ui": 1
            },
            {
                "key": "field_62f0ef62c624c",
                "label": "Alle vises",
                "name": "",
                "type": "message",
                "instructions": "",
                "required": 0,
                "conditional_logic": [
                    [
                        {
                            "field": "field_62f0ef17c624a",
                            "operator": "==",
                            "value": "all"
                        }
                    ]
                ],
                "wrapper": {
                    "width": "",
                    "class": "",
                    "id": ""
                },
                "message": "Alle virksomheder som er sat til at være aktive vises nu på siden.",
                "new_lines": "wpautop",
                "esc_html": 0
            },
            {
                "key": "field_6308990079bc8",
                "label": "Tekst indhold",
                "name": "testimonials",
                "type": "repeater",
                "instructions": "Opret og udfyld diverse testimonials",
                "required": 0,
                "conditional_logic": [
                    [
                        {
                            "field": "field_630898b879bc7",
                            "operator": "==",
                            "value": "content"
                        }
                    ]
                ],
                "wrapper": {
                    "width": "",
                    "class": "",
                    "id": ""
                },
                "collapsed": "",
                "min": 0,
                "max": 0,
                "layout": "block",
                "button_label": "Tilføj",
                "sub_fields": [
                    {
                        "key": "field_6308993879bc9",
                        "label": "Overskrift",
                        "name": "heading",
                        "type": "text",
                        "instructions": "Indtast en kort overskrift (vises i fed skrift)",
                        "required": 1,
                        "conditional_logic": 0,
                        "wrapper": {
                            "width": "",
                            "class": "",
                            "id": ""
                        },
                        "default_value": "",
                        "placeholder": "",
                        "prepend": "",
                        "append": "",
                        "maxlength": ""
                    },
                    {
                        "key": "field_6308995279bca",
                        "label": "Kort tekst",
                        "name": "content",
                        "type": "textarea",
                        "instructions": "Indtast en kort forklarende tekst",
                        "required": 1,
                        "conditional_logic": 0,
                        "wrapper": {
                            "width": "",
                            "class": "",
                            "id": ""
                        },
                        "default_value": "",
                        "placeholder": "",
                        "maxlength": "",
                        "rows": "",
                        "new_lines": ""
                    }
                ]
            }
        ],
        "location": [
            [
                {
                    "param": "block",
                    "operator": "==",
                    "value": "acf\/logoslider"
                }
            ]
        ],
        "menu_order": 0,
        "position": "normal",
        "style": "default",
        "label_placement": "top",
        "instruction_placement": "label",
        "hide_on_screen": "",
        "active": true,
        "description": "",
        "show_in_rest": 0
    },
    {
        "key": "group_62f0ece6ed926",
        "title": "Ydelser",
        "fields": [
            {
                "key": "field_62f4c1b13e1f1",
                "label": "Oversigt",
                "name": "",
                "type": "tab",
                "instructions": "",
                "required": 0,
                "conditional_logic": 0,
                "wrapper": {
                    "width": "",
                    "class": "",
                    "id": ""
                },
                "placement": "top",
                "endpoint": 0
            },
            {
                "key": "field_62f0ed163b557",
                "label": "Ikon til oversigt",
                "name": "icon",
                "type": "button_group",
                "instructions": "Vælg hvad ikon der skal vises",
                "required": 1,
                "conditional_logic": 0,
                "wrapper": {
                    "width": "50",
                    "class": "",
                    "id": ""
                },
                "choices": {
                    "recruit": "Rekruttering",
                    "resume": "CV",
                    "client": "Rådgivning"
                },
                "allow_null": 0,
                "default_value": "",
                "layout": "horizontal",
                "return_format": "value"
            },
            {
                "key": "field_62f0eff4cf81f",
                "label": "Aktiv",
                "name": "active",
                "type": "button_group",
                "instructions": "Vælg om virksomhed skal være Aktiv",
                "required": 1,
                "conditional_logic": 0,
                "wrapper": {
                    "width": "50",
                    "class": "",
                    "id": ""
                },
                "choices": {
                    "active": "Aktiv",
                    "deactive": "Deaktiveret"
                },
                "allow_null": 0,
                "default_value": "active : Aktiv",
                "layout": "vertical",
                "return_format": "value"
            },
            {
                "key": "field_62f0ecf13b556",
                "label": "Beskrivelse",
                "name": "desc",
                "type": "wysiwyg",
                "instructions": "Indtast en kort beskrivelse",
                "required": 1,
                "conditional_logic": 0,
                "wrapper": {
                    "width": "",
                    "class": "",
                    "id": ""
                },
                "default_value": "",
                "tabs": "all",
                "toolbar": "full",
                "media_upload": 1,
                "delay": 0
            },
            {
                "key": "field_62f4c1bc3e1f2",
                "label": "Details",
                "name": "",
                "type": "tab",
                "instructions": "",
                "required": 0,
                "conditional_logic": 0,
                "wrapper": {
                    "width": "",
                    "class": "",
                    "id": ""
                },
                "placement": "top",
                "endpoint": 0
            },
            {
                "key": "field_62f4c1e13e1f4",
                "label": "Ikon til oversigt",
                "name": "svg_header",
                "type": "button_group",
                "instructions": "Vælg hvad ikon der skal vises",
                "required": 1,
                "conditional_logic": 0,
                "wrapper": {
                    "width": "50",
                    "class": "",
                    "id": ""
                },
                "choices": {
                    "recruit": "Rekruttering",
                    "advice": "Rådgivning"
                },
                "allow_null": 0,
                "default_value": "",
                "layout": "vertical",
                "return_format": "value"
            },
            {
                "key": "field_62f4c1ce3e1f3",
                "label": "Beskrivelse til detail side",
                "name": "desc_details",
                "type": "wysiwyg",
                "instructions": "Indtast en kort beskrivelse",
                "required": 1,
                "conditional_logic": 0,
                "wrapper": {
                    "width": "",
                    "class": "",
                    "id": ""
                },
                "default_value": "",
                "tabs": "all",
                "toolbar": "full",
                "media_upload": 1,
                "delay": 0
            }
        ],
        "location": [
            [
                {
                    "param": "post_type",
                    "operator": "==",
                    "value": "services"
                }
            ]
        ],
        "menu_order": 0,
        "position": "normal",
        "style": "default",
        "label_placement": "top",
        "instruction_placement": "label",
        "hide_on_screen": "",
        "active": true,
        "description": "",
        "show_in_rest": 0
    },
    {
        "key": "group_62eb8409bedb0",
        "title": "Ydelser[BLOCK]",
        "fields": [
            {
                "key": "field_62eb8409c113d",
                "label": "Overskrift",
                "name": "heading",
                "type": "text",
                "instructions": "Indtast en kort overskrift",
                "required": 1,
                "conditional_logic": 0,
                "wrapper": {
                    "width": "",
                    "class": "",
                    "id": ""
                },
                "default_value": "Hvad kan vi tilbyde",
                "placeholder": "",
                "prepend": "",
                "append": "",
                "maxlength": ""
            },
            {
                "key": "field_62f0f025a01ca",
                "label": "Vælg layout",
                "name": "layout",
                "type": "button_group",
                "instructions": "Vælg layout",
                "required": 0,
                "conditional_logic": 0,
                "wrapper": {
                    "width": "",
                    "class": "",
                    "id": ""
                },
                "choices": {
                    "all": "Alle",
                    "single": "Vælg enkle"
                },
                "allow_null": 0,
                "default_value": "",
                "layout": "horizontal",
                "return_format": "value"
            },
            {
                "key": "field_62f0f031d8ea7",
                "label": "Vælg enkle",
                "name": "singles",
                "type": "post_object",
                "instructions": "",
                "required": 0,
                "conditional_logic": [
                    [
                        {
                            "field": "field_62f0f025a01ca",
                            "operator": "==",
                            "value": "single"
                        }
                    ]
                ],
                "wrapper": {
                    "width": "",
                    "class": "",
                    "id": ""
                },
                "post_type": [
                    "services"
                ],
                "taxonomy": "",
                "allow_null": 0,
                "multiple": 1,
                "return_format": "id",
                "ui": 1
            },
            {
                "key": "field_62f0f043a0ead",
                "label": "Alle vises",
                "name": "",
                "type": "message",
                "instructions": "",
                "required": 0,
                "conditional_logic": [
                    [
                        {
                            "field": "field_62f0f025a01ca",
                            "operator": "==",
                            "value": "all"
                        }
                    ]
                ],
                "wrapper": {
                    "width": "",
                    "class": "",
                    "id": ""
                },
                "message": "Alle virksomheder som er sat til at være aktive vises nu på siden.",
                "new_lines": "wpautop",
                "esc_html": 0
            }
        ],
        "location": [
            [
                {
                    "param": "block",
                    "operator": "==",
                    "value": "acf\/services"
                }
            ]
        ],
        "menu_order": 0,
        "position": "normal",
        "style": "default",
        "label_placement": "top",
        "instruction_placement": "label",
        "hide_on_screen": "",
        "active": true,
        "description": "",
        "show_in_rest": 0
    },
    {
        "key": "group_62f37cdcd4e4a",
        "title": "Ydelser[Options]",
        "fields": [
            {
                "key": "field_62f37efe5104a",
                "label": "Billede",
                "name": "serivces_image",
                "type": "image",
                "instructions": "Vælg\/upload et billede",
                "required": 1,
                "conditional_logic": 0,
                "wrapper": {
                    "width": "25",
                    "class": "",
                    "id": ""
                },
                "return_format": "array",
                "preview_size": "thumbnail",
                "library": "all",
                "min_width": "",
                "min_height": "",
                "min_size": "",
                "max_width": "",
                "max_height": "",
                "max_size": "",
                "mime_types": ""
            },
            {
                "key": "field_62f37f035104b",
                "label": "Billede tekst",
                "name": "serivces_text",
                "type": "wysiwyg",
                "instructions": "Indtast og formatter en kort banner tekst",
                "required": 1,
                "conditional_logic": 0,
                "wrapper": {
                    "width": "75",
                    "class": "",
                    "id": ""
                },
                "default_value": "",
                "tabs": "all",
                "toolbar": "full",
                "media_upload": 0,
                "delay": 0
            },
            {
                "key": "field_62f4e1c6aa128",
                "label": "Overskrift",
                "name": "services_heading",
                "type": "text",
                "instructions": "Indtast en kort overskrift",
                "required": 0,
                "conditional_logic": 0,
                "wrapper": {
                    "width": "",
                    "class": "",
                    "id": ""
                },
                "default_value": "",
                "placeholder": "",
                "prepend": "",
                "append": "",
                "maxlength": ""
            },
            {
                "key": "field_62ff54da28f50",
                "label": "Footer",
                "name": "services_footer",
                "type": "text",
                "instructions": "Indtast en kort tekst",
                "required": 0,
                "conditional_logic": 0,
                "wrapper": {
                    "width": "",
                    "class": "",
                    "id": ""
                },
                "default_value": "",
                "placeholder": "",
                "prepend": "",
                "append": "",
                "maxlength": ""
            }
        ],
        "location": [
            [
                {
                    "param": "options_page",
                    "operator": "==",
                    "value": "acf-options-ydelser-arkiv"
                }
            ]
        ],
        "menu_order": 0,
        "position": "normal",
        "style": "default",
        "label_placement": "top",
        "instruction_placement": "label",
        "hide_on_screen": "",
        "active": true,
        "description": "",
        "show_in_rest": 0
    }
]